keyframe_tools/ActivityRunner.py
keyframe_tools/Follower.py
keyframe_tools/IndexLooper.py
keyframe_tools/Mover.py
keyframe_tools/Player.py
keyframe_tools/__init__.py
keyframe_tools/closest_keyframe.py
keyframe_tools/config.py
keyframe_tools/interpolator.py
keyframe_tools/segue_to_mover.py
keyframe_tools/utils.py
tests/__init__.py
tests/test_activity_runner.py
tests/test_closest_keyframe.py
tests/test_follower.py
tests/test_index_looper.py
tests/test_interpolator.py
tests/test_player.py
tests/test_segue_to_mover.py
tests/test_utils.py
keyframe_tools-0.0.1.dist-info/LICENSE.txt
keyframe_tools-0.0.1.dist-info/METADATA
keyframe_tools-0.0.1.dist-info/WHEEL
keyframe_tools-0.0.1.dist-info/top_level.txt
keyframe_tools-0.0.1.dist-info/RECORD
